riki_usermanager/User.py
riki_usermanager/UserManager.py
riki_usermanager/__init__.py
tests/__init__.py
tests/test_user.py
tests/test_user_manager.py
Riki_Usermanager-1.0.2.dist-info/LICENSE
Riki_Usermanager-1.0.2.dist-info/METADATA
Riki_Usermanager-1.0.2.dist-info/WHEEL
Riki_Usermanager-1.0.2.dist-info/top_level.txt
Riki_Usermanager-1.0.2.dist-info/RECORD
