Metadata-Version: 2.1
Name: Riki-Usermanager
Version: 1.0.2
Summary: User Manager utilities for the Riki
Home-page: UNKNOWN
Author: Arseny Poga
Author-email: pogaa1@nku.edu
License: UNKNOWN
Platform: UNKNOWN
